README.md
setup.py
bin/bushi-tmux-runner
bushi/__init__.py
bushi/cmd.py
bushi/io.py
bushi/path.py
bushi/tmux.py
bushi.egg-info/PKG-INFO
bushi.egg-info/SOURCES.txt
bushi.egg-info/dependency_links.txt
bushi.egg-info/top_level.txt