Metadata-Version: 2.1
Name: bushi
Version: 0.3.0
Summary: Linux command line interface package
Home-page: https://gitlab.com/ichiro-its/bushi
Author: Alfi Maulana
Author-email: alfi.maulana.f@gmail.com
License: UNKNOWN
Platform: UNKNOWN
Classifier: Programming Language :: Python :: 3
Classifier: License :: OSI Approved :: MIT License
Classifier: Operating System :: OS Independent
Requires-Python: >=3.6
